{
  "url": "https://e-mobility.ewe.de/",
  "requestedUrl": "https://e-mobility.ewe.de/",
  "timestamp": 1636122514477,
  "ranks": {
    "hundos": 26,
    "performance": 3,
    "accessibility": 17,
    "cumulative": 26
  },
  "lighthouse": {
    "version": "8.6.0",
    "performance": 0.59,
    "accessibility": 0.79,
    "bestPractices": null,
    "seo": null,
    "total": 138
  },
  "firstContentfulPaint": 3481.126,
  "firstMeaningfulPaint": 3973.642,
  "speedIndex": 4780.432814013954,
  "largestContentfulPaint": 6382.750499999998,
  "totalBlockingTime": 199,
  "cumulativeLayoutShift": 0.049290161132812496,
  "timeToInteractive": 7794.362,
  "maxPotentialFirstInputDelay": 139,
  "timeToFirstByte": 163.40999999999997,
  "weight": {
    "summary": "35 requests • 945 KiB",
    "total": 967838,
    "image": 333153,
    "imageCount": 7,
    "script": 398894,
    "scriptCount": 13,
    "document": 10807,
    "font": 45388,
    "fontCount": 3,
    "stylesheet": 71465,
    "stylesheetCount": 4,
    "thirdParty": 152254,
    "thirdPartyCount": 12
  },
  "run": {
    "number": 1,
    "total": 2
  },
  "axe": {
    "passes": 2026,
    "violations": 56
  }
}