{
  "AAeon": {
    "timestamp": 1662733745127
  },
  "AAeon-de": {
    "timestamp": 1662733693091
  },
  "AAeonnext": {
    "timestamp": 1662993019985
  },
  "AAessent": {
    "timestamp": 1662993174858
  },
  "BBenergiedirect": {
    "timestamp": 1662993234336
  },
  "CCvandebron": {
    "timestamp": 1662993252115
  },
  "DDenergiebranche": {
    "timestamp": 1662993302561
  },
  "FFservicepartners": {
    "timestamp": 1662993612291
  },
  "XXenergieanbieter": {
    "timestamp": 1662993819797
  },
  "JJfunnel": {
    "timestamp": 1662993765806
  }
}