{
  "AAeon": {
    "timestamp": 1628259818732
  },
  "AAeon-de": {
    "timestamp": 1628432096295
  },
  "AAeonnext": {
    "timestamp": 1628432221564
  },
  "AAessent": {
    "timestamp": 1628518604737
  },
  "BBenergiedirect": {
    "timestamp": 1628604859735
  },
  "CCvandebron": {
    "timestamp": 1628605106250
  },
  "DDenergiebranche": {
    "timestamp": 1628691405666
  },
  "FFservicepartners": {
    "timestamp": 1628086290315
  },
  "XXenergieanbieter": {
    "timestamp": 1628173044559
  }
}