{
  "url": "https://www.vattenfall.nl/producten/energie/",
  "requestedUrl": "https://www.vattenfall.nl/producten/energie/",
  "timestamp": 1673792125428,
  "ranks": {
    "hundos": 6,
    "performance": 6,
    "accessibility": 3,
    "cumulative": 6
  },
  "lighthouse": {
    "version": "8.6.0",
    "performance": 0.07,
    "accessibility": 0.93,
    "bestPractices": 0.8,
    "seo": 0.93,
    "total": 273
  },
  "firstContentfulPaint": 3173.929,
  "firstMeaningfulPaint": 3970.2239999999997,
  "speedIndex": 10152.254476975448,
  "largestContentfulPaint": 23538.450999999986,
  "totalBlockingTime": 3771,
  "cumulativeLayoutShift": 0.8764404296875,
  "timeToInteractive": 29033.34199999999,
  "maxPotentialFirstInputDelay": 2024,
  "timeToFirstByte": 967.808,
  "weight": {
    "summary": "69 requests • 4,898 KiB",
    "total": 5015246,
    "image": 1791802,
    "imageCount": 11,
    "script": 2702244,
    "scriptCount": 26,
    "document": 13968,
    "font": 401274,
    "fontCount": 11,
    "stylesheet": 87768,
    "stylesheetCount": 2,
    "thirdParty": 274809,
    "thirdPartyCount": 17
  },
  "run": {
    "number": 1,
    "total": 1
  },
  "axe": {
    "passes": 848,
    "violations": 4
  }
}