{
  "url": "https://www.essent.nl/content/particulier/energie-besparen/index.html",
  "requestedUrl": "https://www.essent.nl/content/particulier/energie-besparen/index.html",
  "timestamp": 1627827116087,
  "ranks": {
    "hundos": 10,
    "performance": 3,
    "accessibility": 10,
    "cumulative": 9
  },
  "lighthouse": {
    "version": "8.1.0",
    "performance": 0.28,
    "accessibility": 0.7,
    "bestPractices": 0.6,
    "seo": 0.86,
    "total": 244
  },
  "firstContentfulPaint": 3995.258,
  "firstMeaningfulPaint": 4504.915000000001,
  "speedIndex": 7441.040551795339,
  "largestContentfulPaint": 9766.988999999998,
  "totalBlockingTime": 1198.499999999999,
  "cumulativeLayoutShift": 0,
  "timeToInteractive": 13355.856500000002,
  "maxPotentialFirstInputDelay": 1110.999999999999,
  "timeToFirstByte": 175.99400000000003,
  "weight": {
    "summary": "61 requests • 2,303 KiB",
    "total": 2358508,
    "image": 1093252,
    "imageCount": 19,
    "script": 619697,
    "scriptCount": 22,
    "document": 13001,
    "font": 198948,
    "fontCount": 5,
    "stylesheet": 78414,
    "stylesheetCount": 2,
    "thirdParty": 391978,
    "thirdPartyCount": 27
  },
  "run": {
    "number": 1,
    "total": 1
  },
  "axe": {
    "passes": 702,
    "violations": 52
  }
}